problems/other_uart/clock-divider.v
module clock_divider #(
  parameter NATIVE_CLK_FREQUENCY = 1,
  parameter TARGET_CLK_FREQUENCY = 1,
  parameter DELAYED_START = 0
) (input wire clk, input wire reset, output wire target_clk);
   parameter REDUCTION_RATE = NATIVE_CLK_FREQUENCY / TARGET_CLK_FREQUENCY;
   
   reg [$clog2(REDUCTION_RATE):0]counter = 0;

   always @(posedge clk, posedge reset)
       counter <= reset? DELAYED_START : counter + 1;

   assign target_clk = counter == REDUCTION_RATE;

   // NOTE: Question, is it ok to use negedge clk?
   always @(negedge clk)
       if (target_clk)
           counter <= 0;
endmodule

problems/other_uart/uart-receiver.v
module uart_receiver
#(
  parameter NATIVE_CLK_FREQUENCY = 1000000000,
  parameter BAUDRATE = 9600,
  parameter FRAME_DATA_LENGTH = 8,
  parameter BIG_ENDIAN = 0
) (input clk, input rx, output reg [0:FRAME_DATA_LENGTH - 1]received_data = 0, output busy);

    reg reset = 1;
    clock_divider #(
        .NATIVE_CLK_FREQUENCY(NATIVE_CLK_FREQUENCY),
        .TARGET_CLK_FREQUENCY(BAUDRATE),
        .DELAYED_START(1)
    ) clk_div(.clk(clk), .reset(reset), .target_clk(target_clk));

    // 0 is considered idle, another three are for initial 0 and for the last 1
    parameter MAX_RECEIVED_BIT = FRAME_DATA_LENGTH + 2;
    reg [0:$clog2(MAX_RECEIVED_BIT) - 1]received_bit = 0;
       
    assign busy = received_bit != 0;
    assign got_new_transmission = !rx && !busy;

    always @(negedge clk)
        if (got_new_transmission) begin
            received_bit <= 1;
            reset <= 0;
            received_data <= 0; // This is kind of unnecessary, not sure if it impacts syntesis though 
        end else if (!busy)
            reset <= 1;

    always @(negedge target_clk)
        if (busy) begin
            if (received_bit != 1)
                received_data[BIG_ENDIAN ? received_bit - 2 : (FRAME_DATA_LENGTH - 1) - (received_bit - 2)] <= rx;
            received_bit <= (received_bit == MAX_RECEIVED_BIT) ? 0 : received_bit + 1;
        end
endmodule

problems/other_uart/uart-transmitter.v
module uart_transmitter
#(
  parameter NATIVE_CLK_FREQUENCY = 1000000000,
  parameter BAUDRATE = 9600,
  parameter FRAME_DATA_LENGTH = 8,
  parameter BIG_ENDIAN = 0
) (input clk, input sending, input [0:FRAME_DATA_LENGTH - 1]data, output busy, output reg tx = 1);

    reg reset = 0;
    clock_divider #(
        .NATIVE_CLK_FREQUENCY(NATIVE_CLK_FREQUENCY),
        .TARGET_CLK_FREQUENCY(BAUDRATE)
    ) clk_div(.clk(clk), .reset(reset), .target_clk(target_clk));

    // 0 is considered idle, another three are for initial 0, 1 and for the last 1
    parameter MAX_TRANSMITTED_BIT = FRAME_DATA_LENGTH + 3;

    reg [0:$clog2(MAX_TRANSMITTED_BIT) - 1]transmitted_bit = 0;

    assign busy = transmitted_bit != 0;
    assign got_new_data = sending && !busy;

    reg [0:MAX_TRANSMITTED_BIT - 1]saved_data = { 1'b0, {FRAME_DATA_LENGTH{1'b0}}, 2'b11 };
    always @(posedge clk) begin
        if (got_new_data) begin
            if (!BIG_ENDIAN)
                for (integer i = 0; i < FRAME_DATA_LENGTH; i ++)
                    saved_data[i + 1] <= data[FRAME_DATA_LENGTH - 1 - i];
            else
                saved_data[1:FRAME_DATA_LENGTH] <= data;
            transmitted_bit <= 1;

            tx <= 1; // Send transmission start signal
        end

        reset <= got_new_data;
    end

    always @(negedge target_clk)
        if (busy) begin
            tx <= saved_data[transmitted_bit - 1];
            transmitted_bit <= (transmitted_bit == MAX_TRANSMITTED_BIT) ? 0 : transmitted_bit + 1;
        end else
            tx <= 1'b1;
endmodule

problems/other_uart/testbench.v
`timescale 1 ns / 100 ps

module testbench();
    reg clk = 1'b0; always #1 clk = ~clk;

    reg [0:7]data = 8'b0;
    reg sending = 1'b0;

    wire tx;
    uart_transmitter #(.NATIVE_CLK_FREQUENCY(100000), .BAUDRATE(9600))
        uart_tx(.clk(clk), .sending(sending), .data(data), .tx(tx));

    uart_receiver #(.NATIVE_CLK_FREQUENCY(100000), .BAUDRATE(9600))
        uart_rx(.clk(clk), .rx(tx));

    initial begin
        $dumpvars;
        $display("Test started...");
        data =  15; sending = 1; #2 sending = 0; #256
        data = 121; sending = 1; #2 sending = 0; #256
        data = 170; sending = 1; #2 sending = 0; #256
        data = 255; sending = 1; #2 sending = 0; #256
        data =  79; sending = 1; #2 sending = 0; #256
        data =  32; sending = 1; #2 sending = 0; #256
        #4096 $finish;
    end

endmodule

problems/other_uart/dump.vcd
$date
	Mon May 13 06:55:33 2024
$end
$version
	Icarus Verilog
$end
$timescale
	100ps
$end
$scope module testbench $end
$var wire 1 ! tx $end
$var reg 1 " clk $end
$var reg 8 # data [0:7] $end
$var reg 1 $ sending $end
$scope module uart_rx $end
$var wire 1 " clk $end
$var wire 1 % got_new_transmission $end
$var wire 1 & target_clk $end
$var wire 1 ! rx $end
$var wire 1 ' busy $end
$var parameter 32 ( BAUDRATE $end
$var parameter 32 ) BIG_ENDIAN $end
$var parameter 32 * FRAME_DATA_LENGTH $end
$var parameter 33 + MAX_RECEIVED_BIT $end
$var parameter 32 , NATIVE_CLK_FREQUENCY $end
$var reg 4 - received_bit [0:3] $end
$var reg 8 . received_data [0:7] $end
$var reg 1 / reset $end
$scope module clk_div $end
$var wire 1 " clk $end
$var wire 1 / reset $end
$var wire 1 & target_clk $end
$var parameter 32 0 DELAYED_START $end
$var parameter 32 1 NATIVE_CLK_FREQUENCY $end
$var parameter 32 2 REDUCTION_RATE $end
$var parameter 32 3 TARGET_CLK_FREQUENCY $end
$var reg 5 4 counter [4:0] $end
$upscope $end
$upscope $end
$scope module uart_tx $end
$var wire 1 " clk $end
$var wire 8 5 data [0:7] $end
$var wire 1 6 got_new_data $end
$var wire 1 $ sending $end
$var wire 1 7 target_clk $end
$var wire 1 8 busy $end
$var parameter 32 9 BAUDRATE $end
$var parameter 32 : BIG_ENDIAN $end
$var parameter 32 ; FRAME_DATA_LENGTH $end
$var parameter 33 < MAX_TRANSMITTED_BIT $end
$var parameter 32 = NATIVE_CLK_FREQUENCY $end
$var reg 1 > reset $end
$var reg 11 ? saved_data [0:10] $end
$var reg 4 @ transmitted_bit [0:3] $end
$var reg 1 ! tx $end
$scope module clk_div $end
$var wire 1 " clk $end
$var wire 1 > reset $end
$var wire 1 7 target_clk $end
$var parameter 32 A DELAYED_START $end
$var parameter 32 B NATIVE_CLK_FREQUENCY $end
$var parameter 32 C REDUCTION_RATE $end
$var parameter 32 D TARGET_CLK_FREQUENCY $end
$var reg 5 E counter [4:0] $end
$upscope $end
$scope begin $ivl_for_loop0 $end
$var integer 32 F i [31:0] $end
$upscope $end
$upscope $end
$upscope $end
$enddefinitions $end
$comment Show the parameter values. $end
$dumpall
b10010110000000 D
b1010 C
b11000011010100000 B
b0 A
b11000011010100000 =
b1011 <
b1000 ;
b0 :
b10010110000000 9
b10010110000000 3
b1010 2
b11000011010100000 1
b1 0
b11000011010100000 ,
b1010 +
b1000 *
b0 )
b10010110000000 (
$end
#0
$dumpvars
bx F
b0 E
b0 @
b11 ?
0>
08
07
16
b1111 5
b1 4
1/
b0 .
b0 -
0'
0&
0%
1$
b1111 #
0"
1!
$end
#10
06
1>
18
b1 @
b1111000011 ?
b0 E
b1000 F
1"
#20
0"
0$
#30
0>
1"
#40
0"
#50
b1 E
1"
#60
0"
#70
b10 E
1"
#80
0"
#90
b11 E
1"
#100
0"
#110
b100 E
1"
#120
0"
#130
b101 E
1"
#140
0"
#150
b110 E
1"
#160
0"
#170
b111 E
1"
#180
0"
#190
b1000 E
1"
#200
0"
#210
b1001 E
1"
#220
0"
#230
17
b1010 E
1"
#240
1%
b10 @
0!
07
b0 E
0"
#250
b1 E
1"
#260
0%
0/
1'
b1 -
0"
#270
b10 4
b10 E
1"
#280
0"
#290
b11 4
b11 E
1"
#300
0"
#310
b100 4
b100 E
1"
#320
0"
#330
b101 4
b101 E
1"
#340
0"
#350
b110 4
b110 E
1"
#360
0"
#370
b111 4
b111 E
1"
#380
0"
#390
b1000 4
b1000 E
1"
#400
0"
#410
b1001 4
b1001 E
1"
#420
0"
#430
1&
b1010 4
17
b1010 E
1"
#440
b11 @
1!
b10 -
07
b0 E
0&
b0 4
0"
#450
b1 4
b1 E
1"
#460
0"
#470
b10 4
b10 E
1"
#480
0"
#490
b11 4
b11 E
1"
#500
0"
#510
b100 4
b100 E
1"
#520
0"
#530
b101 4
b101 E
1"
#540
0"
#550
b110 4
b110 E
1"
#560
0"
#570
b111 4
b111 E
1"
#580
0"
#590
b1000 4
b1000 E
1"
#600
0"
#610
b1001 4
b1001 E
1"
#620
0"
#630
1&
b1010 4
17
b1010 E
1"
#640
b100 @
b11 -
b1 .
07
b0 E
0&
b0 4
0"
#650
b1 4
b1 E
1"
#660
0"
#670
b10 4
b10 E
1"
#680
0"
#690
b11 4
b11 E
1"
#700
0"
#710
b100 4
b100 E
1"
#720
0"
#730
b101 4
b101 E
1"
#740
0"
#750
b110 4
b110 E
1"
#760
0"
#770
b111 4
b111 E
1"
#780
0"
#790
b1000 4
b1000 E
1"
#800
0"
#810
b1001 4
b1001 E
1"
#820
0"
#830
1&
b1010 4
17
b1010 E
1"
#840
b101 @
b100 -
b11 .
07
b0 E
0&
b0 4
0"
#850
b1 4
b1 E
1"
#860
0"
#870
b10 4
b10 E
1"
#880
0"
#890
b11 4
b11 E
1"
#900
0"
#910
b100 4
b100 E
1"
#920
0"
#930
b101 4
b101 E
1"
#940
0"
#950
b110 4
b110 E
1"
#960
0"
#970
b111 4
b111 E
1"
#980
0"
#990
b1000 4
b1000 E
1"
#1000
0"
#1010
b1001 4
b1001 E
1"
#1020
0"
#1030
1&
b1010 4
17
b1010 E
1"
#1040
b110 @
b101 -
b111 .
07
b0 E
0&
b0 4
0"
#1050
b1 4
b1 E
1"
#1060
0"
#1070
b10 4
b10 E
1"
#1080
0"
#1090
b11 4
b11 E
1"
#1100
0"
#1110
b100 4
b100 E
1"
#1120
0"
#1130
b101 4
b101 E
1"
#1140
0"
#1150
b110 4
b110 E
1"
#1160
0"
#1170
b111 4
b111 E
1"
#1180
0"
#1190
b1000 4
b1000 E
1"
#1200
0"
#1210
b1001 4
b1001 E
1"
#1220
0"
#1230
1&
b1010 4
17
b1010 E
1"
#1240
b111 @
0!
b110 -
b1111 .
07
b0 E
0&
b0 4
0"
#1250
b1 4
b1 E
1"
#1260
0"
#1270
b10 4
b10 E
1"
#1280
0"
#1290
b11 4
b11 E
1"
#1300
0"
#1310
b100 4
b100 E
1"
#1320
0"
#1330
b101 4
b101 E
1"
#1340
0"
#1350
b110 4
b110 E
1"
#1360
0"
#1370
b111 4
b111 E
1"
#1380
0"
#1390
b1000 4
b1000 E
1"
#1400
0"
#1410
b1001 4
b1001 E
1"
#1420
0"
#1430
1&
b1010 4
17
b1010 E
1"
#1440
b1000 @
b111 -
07
b0 E
0&
b0 4
0"
#1450
b1 4
b1 E
1"
#1460
0"
#1470
b10 4
b10 E
1"
#1480
0"
#1490
b11 4
b11 E
1"
#1500
0"
#1510
b100 4
b100 E
1"
#1520
0"
#1530
b101 4
b101 E
1"
#1540
0"
#1550
b110 4
b110 E
1"
#1560
0"
#1570
b111 4
b111 E
1"
#1580
0"
#1590
b1000 4
b1000 E
1"
#1600
0"
#1610
b1001 4
b1001 E
1"
#1620
0"
#1630
1&
b1010 4
17
b1010 E
1"
#1640
b1001 @
b1000 -
07
b0 E
0&
b0 4
0"
#1650
b1 4
b1 E
1"
#1660
0"
#1670
b10 4
b10 E
1"
#1680
0"
#1690
b11 4
b11 E
1"
#1700
0"
#1710
b100 4
b100 E
1"
#1720
0"
#1730
b101 4
b101 E
1"
#1740
0"
#1750
b110 4
b110 E
1"
#1760
0"
#1770
b111 4
b111 E
1"
#1780
0"
#1790
b1000 4
b1000 E
1"
#1800
0"
#1810
b1001 4
b1001 E
1"
#1820
0"
#1830
1&
b1010 4
17
b1010 E
1"
#1840
b1010 @
b1001 -
07
b0 E
0&
b0 4
0"
#1850
b1 4
b1 E
1"
#1860
0"
#1870
b10 4
b10 E
1"
#1880
0"
#1890
b11 4
b11 E
1"
#1900
0"
#1910
b100 4
b100 E
1"
#1920
0"
#1930
b101 4
b101 E
1"
#1940
0"
#1950
b110 4
b110 E
1"
#1960
0"
#1970
b111 4
b111 E
1"
#1980
0"
#1990
b1000 4
b1000 E
1"
#2000
0"
#2010
b1001 4
b1001 E
1"
#2020
0"
#2030
1&
b1010 4
17
b1010 E
1"
#2040
b1011 @
1!
b1010 -
07
b0 E
0&
b0 4
0"
#2050
b1 4
b1 E
1"
#2060
0"
#2070
b10 4
b10 E
1"
#2080
0"
#2090
b11 4
b11 E
1"
#2100
0"
#2110
b100 4
b100 E
1"
#2120
0"
#2130
b101 4
b101 E
1"
#2140
0"
#2150
b110 4
b110 E
1"
#2160
0"
#2170
b111 4
b111 E
1"
#2180
0"
#2190
b1000 4
b1000 E
1"
#2200
0"
#2210
b1001 4
b1001 E
1"
#2220
0"
#2230
1&
b1010 4
17
b1010 E
1"
#2240
08
b0 @
0'
b0 -
07
b0 E
0&
b0 4
0"
#2250
b1 4
b1 E
1"
#2260
1/
0"
#2270
b10 E
1"
#2280
0"
#2290
b11 E
1"
#2300
0"
#2310
b100 E
1"
#2320
0"
#2330
b101 E
1"
#2340
0"
#2350
b110 E
1"
#2360
0"
#2370
b111 E
1"
#2380
0"
#2390
b1000 E
1"
#2400
0"
#2410
b1001 E
1"
#2420
0"
#2430
17
b1010 E
1"
#2440
07
b0 E
0"
#2450
b1 E
1"
#2460
0"
#2470
b10 E
1"
#2480
0"
#2490
b11 E
1"
#2500
0"
#2510
b100 E
1"
#2520
0"
#2530
b101 E
1"
#2540
0"
#2550
b110 E
1"
#2560
0"
#2570
b111 E
1"
#2580
16
0"
1$
b1111001 #
b1111001 5
#2590
06
1>
18
b1 @
b1001111011 ?
b0 E
b1000 F
1"
#2600
0"
0$
#2610
0>
1"
#2620
0"
#2630
b1 E
1"
#2640
0"
#2650
b10 E
1"
#2660
0"
#2670
b11 E
1"
#2680
0"
#2690
b100 E
1"
#2700
0"
#2710
b101 E
1"
#2720
0"
#2730
b110 E
1"
#2740
0"
#2750
b111 E
1"
#2760
0"
#2770
b1000 E
1"
#2780
0"
#2790
b1001 E
1"
#2800
0"
#2810
17
b1010 E
1"
#2820
1%
b10 @
0!
07
b0 E
0"
#2830
b1 E
1"
#2840
0%
b0 .
0/
1'
b1 -
0"
#2850
b10 4
b10 E
1"
#2860
0"
#2870
b11 4
b11 E
1"
#2880
0"
#2890
b100 4
b100 E
1"
#2900
0"
#2910
b101 4
b101 E
1"
#2920
0"
#2930
b110 4
b110 E
1"
#2940
0"
#2950
b111 4
b111 E
1"
#2960
0"
#2970
b1000 4
b1000 E
1"
#2980
0"
#2990
b1001 4
b1001 E
1"
#3000
0"
#3010
1&
b1010 4
17
b1010 E
1"
#3020
b10 -
b11 @
1!
0&
b0 4
07
b0 E
0"
#3030
b1 4
b1 E
1"
#3040
0"
#3050
b10 4
b10 E
1"
#3060
0"
#3070
b11 4
b11 E
1"
#3080
0"
#3090
b100 4
b100 E
1"
#3100
0"
#3110
b101 4
b101 E
1"
#3120
0"
#3130
b110 4
b110 E
1"
#3140
0"
#3150
b111 4
b111 E
1"
#3160
0"
#3170
b1000 4
b1000 E
1"
#3180
0"
#3190
b1001 4
b1001 E
1"
#3200
0"
#3210
1&
b1010 4
17
b1010 E
1"
#3220
b11 -
b1 .
b100 @
0!
0&
b0 4
07
b0 E
0"
#3230
b1 4
b1 E
1"
#3240
0"
#3250
b10 4
b10 E
1"
#3260
0"
#3270
b11 4
b11 E
1"
#3280
0"
#3290
b100 4
b100 E
1"
#3300
0"
#3310
b101 4
b101 E
1"
#3320
0"
#3330
b110 4
b110 E
1"
#3340
0"
#3350
b111 4
b111 E
1"
#3360
0"
#3370
b1000 4
b1000 E
1"
#3380
0"
#3390
b1001 4
b1001 E
1"
#3400
0"
#3410
1&
b1010 4
17
b1010 E
1"
#3420
b100 -
b101 @
0&
b0 4
07
b0 E
0"
#3430
b1 4
b1 E
1"
#3440
0"
#3450
b10 4
b10 E
1"
#3460
0"
#3470
b11 4
b11 E
1"
#3480
0"
#3490
b100 4
b100 E
1"
#3500
0"
#3510
b101 4
b101 E
1"
#3520
0"
#3530
b110 4
b110 E
1"
#3540
0"
#3550
b111 4
b111 E
1"
#3560
0"
#3570
b1000 4
b1000 E
1"
#3580
0"
#3590
b1001 4
b1001 E
1"
#3600
0"
#3610
1&
b1010 4
17
b1010 E
1"
#3620
b101 -
b110 @
1!
0&
b0 4
07
b0 E
0"
#3630
b1 4
b1 E
1"
#3640
0"
#3650
b10 4
b10 E
1"
#3660
0"
#3670
b11 4
b11 E
1"
#3680
0"
#3690
b100 4
b100 E
1"
#3700
0"
#3710
b101 4
b101 E
1"
#3720
0"
#3730
b110 4
b110 E
1"
#3740
0"
#3750
b111 4
b111 E
1"
#3760
0"
#3770
b1000 4
b1000 E
1"
#3780
0"
#3790
b1001 4
b1001 E
1"
#3800
0"
#3810
1&
b1010 4
17
b1010 E
1"
#3820
b110 -
b1001 .
b111 @
0&
b0 4
07
b0 E
0"
#3830
b1 4
b1 E
1"
#3840
0"
#3850
b10 4
b10 E
1"
#3860
0"
#3870
b11 4
b11 E
1"
#3880
0"
#3890
b100 4
b100 E
1"
#3900
0"
#3910
b101 4
b101 E
1"
#3920
0"
#3930
b110 4
b110 E
1"
#3940
0"
#3950
b111 4
b111 E
1"
#3960
0"
#3970
b1000 4
b1000 E
1"
#3980
0"
#3990
b1001 4
b1001 E
1"
#4000
0"
#4010
1&
b1010 4
17
b1010 E
1"
#4020
b111 -
b11001 .
b1000 @
0&
b0 4
07
b0 E
0"
#4030
b1 4
b1 E
1"
#4040
0"
#4050
b10 4
b10 E
1"
#4060
0"
#4070
b11 4
b11 E
1"
#4080
0"
#4090
b100 4
b100 E
1"
#4100
0"
#4110
b101 4
b101 E
1"
#4120
0"
#4130
b110 4
b110 E
1"
#4140
0"
#4150
b111 4
b111 E
1"
#4160
0"
#4170
b1000 4
b1000 E
1"
#4180
0"
#4190
b1001 4
b1001 E
1"
#4200
0"
#4210
1&
b1010 4
17
b1010 E
1"
#4220
b1000 -
b111001 .
b1001 @
0&
b0 4
07
b0 E
0"
#4230
b1 4
b1 E
1"
#4240
0"
#4250
b10 4
b10 E
1"
#4260
0"
#4270
b11 4
b11 E
1"
#4280
0"
#4290
b100 4
b100 E
1"
#4300
0"
#4310
b101 4
b101 E
1"
#4320
0"
#4330
b110 4
b110 E
1"
#4340
0"
#4350
b111 4
b111 E
1"
#4360
0"
#4370
b1000 4
b1000 E
1"
#4380
0"
#4390
b1001 4
b1001 E
1"
#4400
0"
#4410
1&
b1010 4
17
b1010 E
1"
#4420
b1001 -
b1111001 .
b1010 @
0!
0&
b0 4
07
b0 E
0"
#4430
b1 4
b1 E
1"
#4440
0"
#4450
b10 4
b10 E
1"
#4460
0"
#4470
b11 4
b11 E
1"
#4480
0"
#4490
b100 4
b100 E
1"
#4500
0"
#4510
b101 4
b101 E
1"
#4520
0"
#4530
b110 4
b110 E
1"
#4540
0"
#4550
b111 4
b111 E
1"
#4560
0"
#4570
b1000 4
b1000 E
1"
#4580
0"
#4590
b1001 4
b1001 E
1"
#4600
0"
#4610
1&
b1010 4
17
b1010 E
1"
#4620
b1010 -
b1011 @
1!
0&
b0 4
07
b0 E
0"
#4630
b1 4
b1 E
1"
#4640
0"
#4650
b10 4
b10 E
1"
#4660
0"
#4670
b11 4
b11 E
1"
#4680
0"
#4690
b100 4
b100 E
1"
#4700
0"
#4710
b101 4
b101 E
1"
#4720
0"
#4730
b110 4
b110 E
1"
#4740
0"
#4750
b111 4
b111 E
1"
#4760
0"
#4770
b1000 4
b1000 E
1"
#4780
0"
#4790
b1001 4
b1001 E
1"
#4800
0"
#4810
1&
b1010 4
17
b1010 E
1"
#4820
0'
b0 -
08
b0 @
0&
b0 4
07
b0 E
0"
#4830
b1 4
b1 E
1"
#4840
1/
0"
#4850
b10 E
1"
#4860
0"
#4870
b11 E
1"
#4880
0"
#4890
b100 E
1"
#4900
0"
#4910
b101 E
1"
#4920
0"
#4930
b110 E
1"
#4940
0"
#4950
b111 E
1"
#4960
0"
#4970
b1000 E
1"
#4980
0"
#4990
b1001 E
1"
#5000
0"
#5010
17
b1010 E
1"
#5020
07
b0 E
0"
#5030
b1 E
1"
#5040
0"
#5050
b10 E
1"
#5060
0"
#5070
b11 E
1"
#5080
0"
#5090
b100 E
1"
#5100
0"
#5110
b101 E
1"
#5120
0"
#5130
b110 E
1"
#5140
0"
#5150
b111 E
1"
#5160
16
0"
1$
b10101010 #
b10101010 5
#5170
06
1>
18
b1 @
b101010111 ?
b0 E
b1000 F
1"
#5180
0"
0$
#5190
0>
1"
#5200
0"
#5210
b1 E
1"
#5220
0"
#5230
b10 E
1"
#5240
0"
#5250
b11 E
1"
#5260
0"
#5270
b100 E
1"
#5280
0"
#5290
b101 E
1"
#5300
0"
#5310
b110 E
1"
#5320
0"
#5330
b111 E
1"
#5340
0"
#5350
b1000 E
1"
#5360
0"
#5370
b1001 E
1"
#5380
0"
#5390
17
b1010 E
1"
#5400
1%
b10 @
0!
07
b0 E
0"
#5410
b1 E
1"
#5420
0%
b0 .
0/
1'
b1 -
0"
#5430
b10 4
b10 E
1"
#5440
0"
#5450
b11 4
b11 E
1"
#5460
0"
#5470
b100 4
b100 E
1"
#5480
0"
#5490
b101 4
b101 E
1"
#5500
0"
#5510
b110 4
b110 E
1"
#5520
0"
#5530
b111 4
b111 E
1"
#5540
0"
#5550
b1000 4
b1000 E
1"
#5560
0"
#5570
b1001 4
b1001 E
1"
#5580
0"
#5590
1&
b1010 4
17
b1010 E
1"
#5600
b11 @
b10 -
07
b0 E
0&
b0 4
0"
#5610
b1 4
b1 E
1"
#5620
0"
#5630
b10 4
b10 E
1"
#5640
0"
#5650
b11 4
b11 E
1"
#5660
0"
#5670
b100 4
b100 E
1"
#5680
0"
#5690
b101 4
b101 E
1"
#5700
0"
#5710
b110 4
b110 E
1"
#5720
0"
#5730
b111 4
b111 E
1"
#5740
0"
#5750
b1000 4
b1000 E
1"
#5760
0"
#5770
b1001 4
b1001 E
1"
#5780
0"
#5790
1&
b1010 4
17
b1010 E
1"
#5800
b100 @
1!
b11 -
07
b0 E
0&
b0 4
0"
#5810
b1 4
b1 E
1"
#5820
0"
#5830
b10 4
b10 E
1"
#5840
0"
#5850
b11 4
b11 E
1"
#5860
0"
#5870
b100 4
b100 E
1"
#5880
0"
#5890
b101 4
b101 E
1"
#5900
0"
#5910
b110 4
b110 E
1"
#5920
0"
#5930
b111 4
b111 E
1"
#5940
0"
#5950
b1000 4
b1000 E
1"
#5960
0"
#5970
b1001 4
b1001 E
1"
#5980
0"
#5990
1&
b1010 4
17
b1010 E
1"
#6000
b101 @
0!
b100 -
b10 .
07
b0 E
0&
b0 4
0"
#6010
b1 4
b1 E
1"
#6020
0"
#6030
b10 4
b10 E
1"
#6040
0"
#6050
b11 4
b11 E
1"
#6060
0"
#6070
b100 4
b100 E
1"
#6080
0"
#6090
b101 4
b101 E
1"
#6100
0"
#6110
b110 4
b110 E
1"
#6120
0"
#6130
b111 4
b111 E
1"
#6140
0"
#6150
b1000 4
b1000 E
1"
#6160
0"
#6170
b1001 4
b1001 E
1"
#6180
0"
#6190
1&
b1010 4
17
b1010 E
1"
#6200
b110 @
1!
b101 -
07
b0 E
0&
b0 4
0"
#6210
b1 4
b1 E
1"
#6220
0"
#6230
b10 4
b10 E
1"
#6240
0"
#6250
b11 4
b11 E
1"
#6260
0"
#6270
b100 4
b100 E
1"
#6280
0"
#6290
b101 4
b101 E
1"
#6300
0"
#6310
b110 4
b110 E
1"
#6320
0"
#6330
b111 4
b111 E
1"
#6340
0"
#6350
b1000 4
b1000 E
1"
#6360
0"
#6370
b1001 4
b1001 E
1"
#6380
0"
#6390
1&
b1010 4
17
b1010 E
1"
#6400
b111 @
0!
b110 -
b1010 .
07
b0 E
0&
b0 4
0"
#6410
b1 4
b1 E
1"
#6420
0"
#6430
b10 4
b10 E
1"
#6440
0"
#6450
b11 4
b11 E
1"
#6460
0"
#6470
b100 4
b100 E
1"
#6480
0"
#6490
b101 4
b101 E
1"
#6500
0"
#6510
b110 4
b110 E
1"
#6520
0"
#6530
b111 4
b111 E
1"
#6540
0"
#6550
b1000 4
b1000 E
1"
#6560
0"
#6570
b1001 4
b1001 E
1"
#6580
0"
#6590
1&
b1010 4
17
b1010 E
1"
#6600
b1000 @
1!
b111 -
07
b0 E
0&
b0 4
0"
#6610
b1 4
b1 E
1"
#6620
0"
#6630
b10 4
b10 E
1"
#6640
0"
#6650
b11 4
b11 E
1"
#6660
0"
#6670
b100 4
b100 E
1"
#6680
0"
#6690
b101 4
b101 E
1"
#6700
0"
#6710
b110 4
b110 E
1"
#6720
0"
#6730
b111 4
b111 E
1"
#6740
0"
#6750
b1000 4
b1000 E
1"
#6760
0"
#6770
b1001 4
b1001 E
1"
#6780
0"
#6790
1&
b1010 4
17
b1010 E
1"
#6800
b1001 @
0!
b1000 -
b101010 .
07
b0 E
0&
b0 4
0"
#6810
b1 4
b1 E
1"
#6820
0"
#6830
b10 4
b10 E
1"
#6840
0"
#6850
b11 4
b11 E
1"
#6860
0"
#6870
b100 4
b100 E
1"
#6880
0"
#6890
b101 4
b101 E
1"
#6900
0"
#6910
b110 4
b110 E
1"
#6920
0"
#6930
b111 4
b111 E
1"
#6940
0"
#6950
b1000 4
b1000 E
1"
#6960
0"
#6970
b1001 4
b1001 E
1"
#6980
0"
#6990
1&
b1010 4
17
b1010 E
1"
#7000
b1010 @
1!
b1001 -
07
b0 E
0&
b0 4
0"
#7010
b1 4
b1 E
1"
#7020
0"
#7030
b10 4
b10 E
1"
#7040
0"
#7050
b11 4
b11 E
1"
#7060
0"
#7070
b100 4
b100 E
1"
#7080
0"
#7090
b101 4
b101 E
1"
#7100
0"
#7110
b110 4
b110 E
1"
#7120
0"
#7130
b111 4
b111 E
1"
#7140
0"
#7150
b1000 4
b1000 E
1"
#7160
0"
#7170
b1001 4
b1001 E
1"
#7180
0"
#7190
1&
b1010 4
17
b1010 E
1"
#7200
b1011 @
b1010 -
b10101010 .
07
b0 E
0&
b0 4
0"
#7210
b1 4
b1 E
1"
#7220
0"
#7230
b10 4
b10 E
1"
#7240
0"
#7250
b11 4
b11 E
1"
#7260
0"
#7270
b100 4
b100 E
1"
#7280
0"
#7290
b101 4
b101 E
1"
#7300
0"
#7310
b110 4
b110 E
1"
#7320
0"
#7330
b111 4
b111 E
1"
#7340
0"
#7350
b1000 4
b1000 E
1"
#7360
0"
#7370
b1001 4
b1001 E
1"
#7380
0"
#7390
1&
b1010 4
17
b1010 E
1"
#7400
08
b0 @
0'
b0 -
07
b0 E
0&
b0 4
0"
#7410
b1 4
b1 E
1"
#7420
1/
0"
#7430
b10 E
1"
#7440
0"
#7450
b11 E
1"
#7460
0"
#7470
b100 E
1"
#7480
0"
#7490
b101 E
1"
#7500
0"
#7510
b110 E
1"
#7520
0"
#7530
b111 E
1"
#7540
0"
#7550
b1000 E
1"
#7560
0"
#7570
b1001 E
1"
#7580
0"
#7590
17
b1010 E
1"
#7600
07
b0 E
0"
#7610
b1 E
1"
#7620
0"
#7630
b10 E
1"
#7640
0"
#7650
b11 E
1"
#7660
0"
#7670
b100 E
1"
#7680
0"
#7690
b101 E
1"
#7700
0"
#7710
b110 E
1"
#7720
0"
#7730
b111 E
1"
#7740
16
0"
1$
b11111111 #
b11111111 5
#7750
06
1>
18
b1 @
b1111111111 ?
b0 E
b1000 F
1"
#7760
0"
0$
#7770
0>
1"
#7780
0"
#7790
b1 E
1"
#7800
0"
#7810
b10 E
1"
#7820
0"
#7830
b11 E
1"
#7840
0"
#7850
b100 E
1"
#7860
0"
#7870
b101 E
1"
#7880
0"
#7890
b110 E
1"
#7900
0"
#7910
b111 E
1"
#7920
0"
#7930
b1000 E
1"
#7940
0"
#7950
b1001 E
1"
#7960
0"
#7970
17
b1010 E
1"
#7980
1%
b10 @
0!
07
b0 E
0"
#7990
b1 E
1"
#8000
0%
b0 .
0/
1'
b1 -
0"
#8010
b10 4
b10 E
1"
#8020
0"
#8030
b11 4
b11 E
1"
#8040
0"
#8050
b100 4
b100 E
1"
#8060
0"
#8070
b101 4
b101 E
1"
#8080
0"
#8090
b110 4
b110 E
1"
#8100
0"
#8110
b111 4
b111 E
1"
#8120
0"
#8130
b1000 4
b1000 E
1"
#8140
0"
#8150
b1001 4
b1001 E
1"
#8160
0"
#8170
1&
b1010 4
17
b1010 E
1"
#8180
b10 -
b11 @
1!
0&
b0 4
07
b0 E
0"
#8190
b1 4
b1 E
1"
#8200
0"
#8210
b10 4
b10 E
1"
#8220
0"
#8230
b11 4
b11 E
1"
#8240
0"
#8250
b100 4
b100 E
1"
#8260
0"
#8270
b101 4
b101 E
1"
#8280
0"
#8290
b110 4
b110 E
1"
#8300
0"
#8310
b111 4
b111 E
1"
#8320
0"
#8330
b1000 4
b1000 E
1"
#8340
0"
#8350
b1001 4
b1001 E
1"
#8360
0"
#8370
1&
b1010 4
17
b1010 E
1"
#8380
b11 -
b1 .
b100 @
0&
b0 4
07
b0 E
0"
#8390
b1 4
b1 E
1"
#8400
0"
#8410
b10 4
b10 E
1"
#8420
0"
#8430
b11 4
b11 E
1"
#8440
0"
#8450
b100 4
b100 E
1"
#8460
0"
#8470
b101 4
b101 E
1"
#8480
0"
#8490
b110 4
b110 E
1"
#8500
0"
#8510
b111 4
b111 E
1"
#8520
0"
#8530
b1000 4
b1000 E
1"
#8540
0"
#8550
b1001 4
b1001 E
1"
#8560
0"
