problems/other_uart/clock-divider.v
module clock_divider #(
  parameter NATIVE_CLK_FREQUENCY = 1,
  parameter TARGET_CLK_FREQUENCY = 1
) (input wire clk, input wire reset, output wire target_clk);
   parameter REDUCTION_RATE = NATIVE_CLK_FREQUENCY / TARGET_CLK_FREQUENCY;
   
   reg [$clog2(REDUCTION_RATE):0]counter = 0;

   always @(posedge clk, posedge reset)
       counter <= reset? 0 : counter + 1;

   assign target_clk = counter == REDUCTION_RATE;

   // NOTE: Question, is it ok to use negedge clk?
   always @(negedge clk)
       if (target_clk)
           counter <= 0;
endmodule

problems/other_uart/uart-transmitter.v
module uart_transmitter
#(
  parameter NATIVE_CLK_FREQUENCY = 1000000000,
  parameter BAUDRATE = 9600,
  parameter FRAME_DATA_LENGTH = 8,
  // parameter START_SEQUENCE_LENGTH = 2
  // parameter ENABLE_PARITY_BIT = 0
  parameter ENABLE_BIG_ENDIAN = 1
) (input wire clk, input wire data, output wire tx);

   clock_divider #(
       .NATIVE_CLK_FREQUENCY(NATIVE_CLK_FREQUENCY),
       .TARGET_CLK_FREQUENCY(BAUDRATE)
   ) clk_div(.clk(clk), .target_clk());

   // reg state = INITIAL;
 
   
endmodule

problems/other_uart/clock_divider_testbench.v
`timescale 1 ns / 100 ps

module testbench();
   reg clk = 1'b0; always #1 clk = ~clk;

   reg reset = 1'b0;
   clock_divider #(
       .NATIVE_CLK_FREQUENCY(15),
       .TARGET_CLK_FREQUENCY(5)
   ) clk_div(.clk(clk), .reset(reset));

   initial begin
      $dumpvars;
      $display("Test started...");
      #7  reset = 1;
      #1  reset = 0;
      #15 reset = 1;
      #1  reset = 0;
      #31 reset = 1;
      #1  reset = 0;
      #128 $finish;
   end

endmodule

problems/other_uart/dump.vcd
$date
	Sun May 12 23:12:47 2024
$end
$version
	Icarus Verilog
$end
$timescale
	100ps
$end
$scope module testbench $end
$var reg 1 ! clk $end
$var reg 1 " reset $end
$scope module clk_div $end
$var wire 1 ! clk $end
$var wire 1 " reset $end
$var wire 1 # target_clk $end
$var parameter 32 $ NATIVE_CLK_FREQUENCY $end
$var parameter 32 % REDUCTION_RATE $end
$var parameter 32 & TARGET_CLK_FREQUENCY $end
$var reg 3 ' counter [2:0] $end
$upscope $end
$upscope $end
$scope module uart_transmitter $end
$var wire 1 ( clk $end
$var wire 1 ) data $end
$var wire 1 * tx $end
$var parameter 32 + BAUDRATE $end
$var parameter 32 , ENABLE_BIG_ENDIAN $end
$var parameter 32 - FRAME_DATA_LENGTH $end
$var parameter 32 . NATIVE_CLK_FREQUENCY $end
$scope module clk_div $end
$var wire 1 ( clk $end
$var wire 1 / reset $end
$var wire 1 0 target_clk $end
$var parameter 32 1 NATIVE_CLK_FREQUENCY $end
$var parameter 32 2 REDUCTION_RATE $end
$var parameter 32 3 TARGET_CLK_FREQUENCY $end
$var reg 18 4 counter [17:0] $end
$upscope $end
$upscope $end
$enddefinitions $end
$comment Show the parameter values. $end
$dumpall
b10010110000000 3
b11001011011100110 2
b111011100110101100101000000000 1
b111011100110101100101000000000 .
b1000 -
b1 ,
b10010110000000 +
b101 &
b11 %
b1111 $
$end
#0
$dumpvars
b0 4
00
z/
z*
z)
z(
b0 '
0#
0"
0!
$end
#10
b1 '
1!
#20
0!
#30
b10 '
1!
#40
0!
#50
1#
b11 '
1!
#60
0#
b0 '
0!
#70
1!
1"
#80
0!
0"
#90
b1 '
1!
#100
0!
#110
b10 '
1!
#120
0!
#130
1#
b11 '
1!
#140
0#
b0 '
0!
#150
b1 '
1!
#160
0!
#170
b10 '
1!
#180
0!
#190
1#
b11 '
1!
#200
0#
b0 '
0!
#210
b1 '
1!
#220
0!
#230
b0 '
1!
1"
#240
0!
0"
#250
b1 '
1!
#260
0!
#270
b10 '
1!
#280
0!
#290
1#
b11 '
1!
#300
0#
b0 '
0!
#310
b1 '
1!
#320
0!
#330
b10 '
1!
#340
0!
#350
1#
b11 '
1!
#360
0#
b0 '
0!
#370
b1 '
1!
#380
0!
#390
b10 '
1!
#400
0!
#410
1#
b11 '
1!
#420
0#
b0 '
0!
#430
b1 '
1!
#440
0!
#450
b10 '
1!
#460
0!
#470
1#
b11 '
1!
#480
0#
b0 '
0!
#490
b1 '
1!
#500
0!
#510
b10 '
1!
#520
0!
#530
1#
b11 '
1!
#540
0#
b0 '
0!
#550
1!
1"
#560
0!
0"
#570
b1 '
1!
#580
0!
#590
b10 '
1!
#600
0!
#610
1#
b11 '
1!
#620
0#
b0 '
0!
#630
b1 '
1!
#640
0!
#650
b10 '
1!
#660
0!
#670
1#
b11 '
1!
#680
0#
b0 '
0!
#690
b1 '
1!
#700
0!
#710
b10 '
1!
#720
0!
#730
1#
b11 '
1!
#740
0#
b0 '
0!
#750
b1 '
1!
#760
0!
#770
b10 '
1!
#780
0!
#790
1#
b11 '
1!
#800
0#
b0 '
0!
#810
b1 '
1!
#820
0!
#830
b10 '
1!
#840
0!
#850
1#
b11 '
1!
#860
0#
b0 '
0!
#870
b1 '
1!
#880
0!
#890
b10 '
1!
#900
0!
#910
1#
b11 '
1!
#920
0#
b0 '
0!
#930
b1 '
1!
#940
0!
#950
b10 '
1!
#960
0!
#970
1#
b11 '
1!
#980
0#
b0 '
0!
#990
b1 '
1!
#1000
0!
#1010
b10 '
1!
#1020
0!
#1030
1#
b11 '
1!
#1040
0#
b0 '
0!
#1050
b1 '
1!
#1060
0!
#1070
b10 '
1!
#1080
0!
#1090
1#
b11 '
1!
#1100
0#
b0 '
0!
#1110
b1 '
1!
#1120
0!
#1130
b10 '
1!
#1140
0!
#1150
1#
b11 '
1!
#1160
0#
b0 '
0!
#1170
b1 '
1!
#1180
0!
#1190
b10 '
1!
#1200
0!
#1210
1#
b11 '
1!
#1220
0#
b0 '
0!
#1230
b1 '
1!
#1240
0!
#1250
b10 '
1!
#1260
0!
#1270
1#
b11 '
1!
#1280
0#
b0 '
0!
#1290
b1 '
1!
#1300
0!
#1310
b10 '
1!
#1320
0!
#1330
1#
b11 '
1!
#1340
0#
b0 '
0!
#1350
b1 '
1!
#1360
0!
#1370
b10 '
1!
#1380
0!
#1390
1#
b11 '
1!
#1400
0#
b0 '
0!
#1410
b1 '
1!
#1420
0!
#1430
b10 '
1!
#1440
0!
#1450
1#
b11 '
1!
#1460
0#
b0 '
0!
#1470
b1 '
1!
#1480
0!
#1490
b10 '
1!
#1500
0!
#1510
1#
b11 '
1!
#1520
0#
b0 '
0!
#1530
b1 '
1!
#1540
0!
#1550
b10 '
1!
#1560
0!
#1570
1#
b11 '
1!
#1580
0#
b0 '
0!
#1590
b1 '
1!
#1600
0!
#1610
b10 '
1!
#1620
0!
#1630
1#
b11 '
1!
#1640
0#
b0 '
0!
#1650
b1 '
1!
#1660
0!
#1670
b10 '
1!
#1680
0!
#1690
1#
b11 '
1!
#1700
0#
b0 '
0!
#1710
b1 '
1!
#1720
0!
#1730
b10 '
1!
#1740
0!
#1750
1#
b11 '
1!
#1760
0#
b0 '
0!
#1770
b1 '
1!
#1780
0!
#1790
b10 '
1!
#1800
0!
#1810
1#
b11 '
1!
#1820
0#
b0 '
0!
#1830
b1 '
1!
