problems/other_cpu/alu/alu-commands.v
`define ALU_NONE                                4'b0000
`define ALU_ADD                                 4'b0001
`define ALU_SUB                                 4'b0010
`define ALU_XOR                                 4'b0011
`define ALU_OR                                  4'b0100
`define ALU_AND                                 4'b0101
`define ALU_SLL                                 4'b0110
`define ALU_SRL                                 4'b0111
`define ALU_SRA                                 4'b1000
`define ALU_SLT                                 4'b1001
`define ALU_SLTU                                4'b1010

problems/other_cpu/alu/alu.v
`include "alu-commands.v"

module alu(input [31:0] a, input [31:0] b, input [3:0] operation, output reg [31:0] res);
    wire [31:0] sub = a - b;
    
    always @(*) begin
        case (operation)
            `ALU_NONE : res = a;
            `ALU_ADD  : res = a + b;
            `ALU_SUB  : res = a - b;
            `ALU_XOR  : res = a ^ b;
            `ALU_OR   : res = a | b;
            `ALU_AND  : res = a & b; 
            `ALU_SLL  : res = a << b;
            `ALU_SRL  : res = a >> b;
            `ALU_SRA  : res = { a[31], (a[31:1] >> b) };
            `ALU_SLT  : res = (a[31] != b[31]) ? a[31] : sub[31];
            `ALU_SLTU : res = a < b;
            default   : res = 0;
        endcase
    end
endmodule

problems/other_cpu/alu/alu-testbench.v
`timescale 1 ns / 100 ps
`include "alu-commands.v"

module testbench();

    reg [3:0] operation = 0;
    reg [31:0] a;
    reg [31:0] b;
    wire [31:0] res;

    alu alu(.a(a), .b(b), .res(res), .operation(operation));
    
    initial begin
        $dumpvars;
        a = 5; b = 3;
        #5 operation = `ALU_NONE;
        #5 operation = `ALU_ADD;
        #5 operation = `ALU_SUB;
        #5 operation = `ALU_XOR;
        #5 operation = `ALU_OR;
        #5 operation = `ALU_AND;
        #5 operation = `ALU_SLL;
        #5 operation = `ALU_SRL;
        #5 operation = `ALU_SRA;
        #5 operation = `ALU_SLT;
        #5 operation = `ALU_SLTU;
        #5 a = 124; b = 45;
        #5 operation = `ALU_NONE;
        #5 operation = `ALU_ADD;
        #5 operation = `ALU_SUB;
        #5 operation = `ALU_XOR;
        #5 operation = `ALU_OR;
        #5 operation = `ALU_AND;
        #5 operation = `ALU_SLL;
        #5 operation = `ALU_SRL;
        #5 operation = `ALU_SRA;
        #5 operation = `ALU_SLT;
        #5 operation = `ALU_SLTU;
        #5 a = 4661; b = 15478;
        #5 operation = `ALU_NONE;
        #5 operation = `ALU_ADD;
        #5 operation = `ALU_SUB;
        #5 operation = `ALU_XOR;
        #5 operation = `ALU_OR;
        #5 operation = `ALU_AND;
        #5 operation = `ALU_SLL;
        #5 operation = `ALU_SRL;
        #5 operation = `ALU_SRA;
        #5 operation = `ALU_SLT;
        #5 operation = `ALU_SLTU;
        #5 a = 4294967295; b = 4294967295;
        #5 operation = `ALU_NONE;
        #5 operation = `ALU_ADD;
        #5 operation = `ALU_SUB;
        #5 operation = `ALU_XOR;
        #5 operation = `ALU_OR;
        #5 operation = `ALU_AND;
        #5 operation = `ALU_SLL;
        #5 operation = `ALU_SRL;
        #5 operation = `ALU_SRA;
        #5 operation = `ALU_SLT;
        #5 operation = `ALU_SLTU;
        #5 a = 4294967295; b = 1;
        #5 operation = `ALU_NONE;
        #5 operation = `ALU_ADD;
        #5 operation = `ALU_SUB;
        #5 operation = `ALU_XOR;
        #5 operation = `ALU_OR;
        #5 operation = `ALU_AND;
        #5 operation = `ALU_SLL;
        #5 operation = `ALU_SRL;
        #5 operation = `ALU_SRA;
        #5 operation = `ALU_SLT;
        #5 operation = `ALU_SLTU;
        #5 a = 4290000000; b = 4294967295;
        #5 operation = `ALU_NONE;
        #5 operation = `ALU_ADD;
        #5 operation = `ALU_SUB;
        #5 operation = `ALU_XOR;
        #5 operation = `ALU_OR;
        #5 operation = `ALU_AND;
        #5 operation = `ALU_SLL;
        #5 operation = `ALU_SRL;
        #5 operation = `ALU_SRA;
        #5 operation = `ALU_SLT;
        #5 operation = `ALU_SLTU;
        #5 a = 4291111111; b = 4290000000;
        #5 operation = `ALU_NONE;
        #5 operation = `ALU_ADD;
        #5 operation = `ALU_SUB;
        #5 operation = `ALU_XOR;
        #5 operation = `ALU_OR;
        #5 operation = `ALU_AND;
        #5 operation = `ALU_SLL;
        #5 operation = `ALU_SRL;
        #5 operation = `ALU_SRA;
        #5 operation = `ALU_SLT;
        #5 operation = `ALU_SLTU;
        #5 a = 429111111; b = 4290000000;
        #5 operation = `ALU_NONE;
        #5 operation = `ALU_ADD;
        #5 operation = `ALU_SUB;
        #5 operation = `ALU_XOR;
        #5 operation = `ALU_OR;
        #5 operation = `ALU_AND;
        #5 operation = `ALU_SLL;
        #5 operation = `ALU_SRL;
        #5 operation = `ALU_SRA;
        #5 operation = `ALU_SLT;
        #5 operation = `ALU_SLTU;
        #5 a = 4291111111; b = 429000000;
        #5 operation = `ALU_NONE;
        #5 operation = `ALU_ADD;
        #5 operation = `ALU_SUB;
        #5 operation = `ALU_XOR;
        #5 operation = `ALU_OR;
        #5 operation = `ALU_AND;
        #5 operation = `ALU_SLL;
        #5 operation = `ALU_SRL;
        #5 operation = `ALU_SRA;
        #5 operation = `ALU_SLT;
        #5 operation = `ALU_SLTU;
        #5; $finish;
    end
    
endmodule

problems/other_cpu/alu/dump.vcd
$date
	Mon May 20 03:49:45 2024
$end
$version
	Icarus Verilog
$end
$timescale
	100ps
$end
$scope module testbench $end
$var wire 32 ! res [31:0] $end
$var reg 32 " a [31:0] $end
$var reg 32 # b [31:0] $end
$var reg 4 $ operation [3:0] $end
$scope module alu $end
$var wire 32 % a [31:0] $end
$var wire 32 & b [31:0] $end
$var wire 4 ' operation [3:0] $end
$var wire 32 ( sub [31:0] $end
$var reg 32 ) res [31:0] $end
$upscope $end
$upscope $end
$enddefinitions $end
$comment Show the parameter values. $end
$dumpall
$end
#0
$dumpvars
b101 )
b10 (
b0 '
b11 &
b101 %
b0 $
b11 #
b101 "
b101 !
$end
#100
b1000 !
b1000 )
b1 $
b1 '
#150
b10 !
b10 )
b10 $
b10 '
#200
b110 !
b110 )
b11 $
b11 '
#250
b111 !
b111 )
b100 $
b100 '
#300
b1 !
b1 )
b101 $
b101 '
#350
b101000 !
b101000 )
b110 $
b110 '
#400
b0 !
b0 )
b111 $
b111 '
#450
b1000 $
b1000 '
#500
b1001 $
b1001 '
#550
b1010 $
b1010 '
#600
b101101 #
b101101 &
b1001111 (
b1111100 "
b1111100 %
#650
b1111100 !
b1111100 )
b0 $
b0 '
#700
b10101001 !
b10101001 )
b1 $
b1 '
#750
b1001111 !
b1001111 )
b10 $
b10 '
#800
b1010001 !
b1010001 )
b11 $
b11 '
#850
b1111101 !
b1111101 )
b100 $
b100 '
#900
b101100 !
b101100 )
b101 $
b101 '
#950
b0 !
b0 )
b110 $
b110 '
#1000
b111 $
b111 '
#1050
b1000 $
b1000 '
#1100
b1001 $
b1001 '
#1150
b1010 $
b1010 '
#1200
b1 !
b1 )
b11110001110110 #
b11110001110110 &
b11111111111111111101010110111111 (
b1001000110101 "
b1001000110101 %
#1250
b1001000110101 !
b1001000110101 )
b0 $
b0 '
#1300
b100111010101011 !
b100111010101011 )
b1 $
b1 '
#1350
b11111111111111111101010110111111 !
b11111111111111111101010110111111 )
b10 $
b10 '
#1400
b10111001000011 !
b10111001000011 )
b11 $
b11 '
#1450
b11111001110111 !
b11111001110111 )
b100 $
b100 '
#1500
b1000000110100 !
b1000000110100 )
b101 $
b101 '
#1550
b0 !
b0 )
b110 $
b110 '
#1600
b111 $
b111 '
#1650
b1000 $
b1000 '
#1700
b1 !
b1 )
b1001 $
b1001 '
#1750
b1010 $
b1010 '
#1800
b0 !
b0 )
b11111111111111111111111111111111 #
b11111111111111111111111111111111 &
b0 (
b11111111111111111111111111111111 "
b11111111111111111111111111111111 %
#1850
b11111111111111111111111111111111 !
b11111111111111111111111111111111 )
b0 $
b0 '
#1900
b11111111111111111111111111111110 !
b11111111111111111111111111111110 )
b1 $
b1 '
#1950
b0 !
b0 )
b10 $
b10 '
#2000
b11 $
b11 '
#2050
b11111111111111111111111111111111 !
b11111111111111111111111111111111 )
b100 $
b100 '
#2100
b101 $
b101 '
#2150
b0 !
b0 )
b110 $
b110 '
#2200
b111 $
b111 '
#2250
b10000000000000000000000000000000 !
b10000000000000000000000000000000 )
b1000 $
b1000 '
#2300
b0 !
b0 )
b1001 $
b1001 '
#2350
b1010 $
b1010 '
#2400
b11111111111111111111111111111110 (
b1 #
b1 &
#2450
b11111111111111111111111111111111 !
b11111111111111111111111111111111 )
b0 $
b0 '
#2500
b0 !
b0 )
b1 $
b1 '
#2550
b11111111111111111111111111111110 !
b11111111111111111111111111111110 )
b10 $
b10 '
#2600
b11 $
b11 '
#2650
b11111111111111111111111111111111 !
b11111111111111111111111111111111 )
b100 $
b100 '
#2700
b1 !
b1 )
b101 $
b101 '
#2750
b11111111111111111111111111111110 !
b11111111111111111111111111111110 )
b110 $
b110 '
#2800
b1111111111111111111111111111111 !
b1111111111111111111111111111111 )
b111 $
b111 '
#2850
b10111111111111111111111111111111 !
b10111111111111111111111111111111 )
b1000 $
b1000 '
#2900
b1 !
b1 )
b1001 $
b1001 '
#2950
b0 !
b0 )
b1010 $
b1010 '
#3000
b1 !
b1 )
b11111111111111111111111111111111 #
b11111111111111111111111111111111 &
b11111111101101000011010010000001 (
b11111111101101000011010010000000 "
b11111111101101000011010010000000 %
#3050
b11111111101101000011010010000000 !
b11111111101101000011010010000000 )
b0 $
b0 '
#3100
b11111111101101000011010001111111 !
b11111111101101000011010001111111 )
b1 $
b1 '
#3150
b11111111101101000011010010000001 !
b11111111101101000011010010000001 )
b10 $
b10 '
#3200
b10010111100101101111111 !
b10010111100101101111111 )
b11 $
b11 '
#3250
b11111111111111111111111111111111 !
b11111111111111111111111111111111 )
b100 $
b100 '
#3300
b11111111101101000011010010000000 !
b11111111101101000011010010000000 )
b101 $
b101 '
#3350
b0 !
b0 )
b110 $
b110 '
#3400
b111 $
b111 '
#3450
b10000000000000000000000000000000 !
b10000000000000000000000000000000 )
b1000 $
b1000 '
#3500
b1 !
b1 )
b1001 $
b1001 '
#3550
b1010 $
b1010 '
#3600
b0 !
b0 )
b11111111101101000011010010000000 #
b11111111101101000011010010000000 &
b100001111010001000111 (
b11111111110001010010100011000111 "
b11111111110001010010100011000111 %
#3650
b11111111110001010010100011000111 !
b11111111110001010010100011000111 )
b0 $
b0 '
#3700
b11111111011110010101110101000111 !
b11111111011110010101110101000111 )
b1 $
b1 '
#3750
b100001111010001000111 !
b100001111010001000111 )
b10 $
b10 '
#3800
b11100010001110001000111 !
b11100010001110001000111 )
b11 $
b11 '
#3850
b11111111111101010011110011000111 !
b11111111111101010011110011000111 )
b100 $
b100 '
#3900
b11111111100001000010000010000000 !
b11111111100001000010000010000000 )
b101 $
b101 '
#3950
b0 !
b0 )
b110 $
b110 '
#4000
b111 $
b111 '
#4050
b10000000000000000000000000000000 !
b10000000000000000000000000000000 )
b1000 $
b1000 '
#4100
b0 !
b0 )
b1001 $
b1001 '
#4150
b1010 $
b1010 '
#4200
b1 !
b1 )
b11001110111111000001011000111 (
b11001100100111011011101000111 "
b11001100100111011011101000111 %
#4250
b11001100100111011011101000111 !
b11001100100111011011101000111 )
b0 $
b0 '
#4300
b11001010001111110101111000111 !
b11001010001111110101111000111 )
b1 $
b1 '
#4350
b11001110111111000001011000111 !
b11001110111111000001011000111 )
b10 $
b10 '
#4400
b11100110001001111000001111000111 !
b11100110001001111000001111000111 )
b11 $
b11 '
#4450
b11111111101101111011011111000111 !
b11111111101101111011011111000111 )
b100 $
b100 '
#4500
b11001100100000011010000000000 !
b11001100100000011010000000000 )
b101 $
b101 '
#4550
b0 !
b0 )
b110 $
b110 '
#4600
b111 $
b111 '
#4650
b1000 $
b1000 '
#4700
b1001 $
b1001 '
#4750
b1 !
b1 )
b1010 $
b1010 '
#4800
b0 !
b0 )
b11001100100100000010101000000 #
b11001100100100000010101000000 &
b11100110001100110010001110000111 (
b11111111110001010010100011000111 "
b11111111110001010010100011000111 %
#4850
b11111111110001010010100011000111 !
b11111111110001010010100011000111 )
b0 $
b0 '
#4900
b11001010101110010111000000111 !
b11001010101110010111000000111 )
b1 $
b1 '
#4950
b11100110001100110010001110000111 !
b11100110001100110010001110000111 )
b10 $
b10 '
#5000
b11100110010101110010110110000111 !
b11100110010101110010110110000111 )
b11 $
b11 '
#5050
b11111111110101110010110111000111 !
b11111111110101110010110111000111 )
b100 $
b100 '
#5100
b11001100000000000000001000000 !
b11001100000000000000001000000 )
b101 $
b101 '
#5150
b0 !
b0 )
b110 $
b110 '
#5200
b111 $
b111 '
#5250
b10000000000000000000000000000000 !
b10000000000000000000000000000000 )
b1000 $
b1000 '
#5300
b1 !
b1 )
b1001 $
b1001 '
#5350
b0 !
b0 )
b1010 $
b1010 '
