problems/03_dfa/dfa_two_last_bits_are_01.v
module dfa_two_last_bits_are_01(input clk, input reset, input input_sequence, output condition_met);
   parameter S0 = 3'b001, S1 = 3'b010, S2 = 3'b100;

   reg [2:0] state = S0;
   reg [2:0] next_state;
   always @(negedge clk, posedge reset)
     if (reset) state <= S0;
     else       state <= next_state;

   always @(*)
     case (state)
       S0: if (input_sequence) next_state <= S0;
           else                next_state <= S1;
       S1: if (input_sequence) next_state <= S2;
           else                next_state <= S1;
       S2: if (input_sequence) next_state <= S0;
           else                next_state <= S1;

       // Just to prevent latch generation
       default:                next_state <= S0;
     endcase

   assign condition_met = state == S2;
endmodule

problems/03_dfa/testbench.v
`timescale 1 ns / 100 ps

module testbench();
   reg clk = 1'b0; always #1 clk = ~clk;

   reg input_sequence = 0, reset = 1;
   dfa_two_last_bits_are_01 dfa(.clk(clk), .reset(reset), .input_sequence(input_sequence));

   initial begin
      $dumpvars;
      $display("Test started...");
      #2 reset = 0;
      #2 input_sequence = 0;
      #2 input_sequence = 0;
      #2 input_sequence = 1;
      #2 input_sequence = 0;
      #2 input_sequence = 1;
      #2 input_sequence = 1;
      #2 input_sequence = 0;
      #2 input_sequence = 0;
      #2 input_sequence = 1;
      #4 $finish;
   end
endmodule

problems/03_dfa/dump.vcd
$date
	Tue Apr 23 21:31:04 2024
$end
$version
	Icarus Verilog
$end
$timescale
	100ps
$end
$scope module testbench $end
$var reg 1 ! clk $end
$var reg 1 " input_sequence $end
$var reg 1 # reset $end
$scope module dfa $end
$var wire 1 ! clk $end
$var wire 1 " input_sequence $end
$var wire 1 # reset $end
$var wire 1 $ condition_met $end
$var parameter 3 % S0 $end
$var parameter 3 & S1 $end
$var parameter 3 ' S2 $end
$var reg 3 ( next_state [2:0] $end
$var reg 3 ) state [2:0] $end
$upscope $end
$upscope $end
$enddefinitions $end
$comment Show the parameter values. $end
$dumpall
b100 '
b10 &
b1 %
$end
#0
$dumpvars
b1 )
b10 (
0$
1#
0"
0!
$end
#10
1!
#20
b10 )
0!
0#
#30
1!
#40
0!
#50
1!
#60
0!
#70
1!
#80
b100 (
0!
1"
#90
1!
#100
1$
b100 )
b10 (
0!
0"
#110
1!
#120
0$
b10 )
b100 (
0!
1"
#130
1!
#140
b1 (
1$
b100 )
0!
#150
1!
#160
0$
b1 )
b10 (
0!
0"
#170
1!
#180
b10 )
0!
#190
1!
#200
b100 (
0!
1"
#210
1!
#220
b1 (
1$
b100 )
0!
#230
1!
#240
0$
b1 )
0!
